pycityagent/__init__.py
pycityagent/agent.py
pycityagent/agent_citizen.py
pycityagent/agent_func.py
pycityagent/agent_group.py
pycityagent/simulator.py
pycityagent/utils.py
pycityagent/ac/__init__.py
pycityagent/ac/ac.py
pycityagent/ac/action.py
pycityagent/ac/action_stream.py
pycityagent/ac/hub_actions.py
pycityagent/ac/sim_actions.py
pycityagent/ac/citizen_actions/controled.py
pycityagent/ac/citizen_actions/converse.py
pycityagent/ac/citizen_actions/idle.py
pycityagent/ac/citizen_actions/shop.py
pycityagent/ac/citizen_actions/trip.py
pycityagent/brain/__init__.py
pycityagent/brain/brain.py
pycityagent/brain/brainfc.py
pycityagent/brain/memory.py
pycityagent/brain/scheduler.py
pycityagent/brain/sence.py
pycityagent/brain/static.py
pycityagent/brain/persistence/__init__.py
pycityagent/brain/persistence/social.py
pycityagent/brain/persistence/spatial.py
pycityagent/brain/reason/__init__.py
pycityagent/brain/reason/shop.py
pycityagent/brain/reason/social.py
pycityagent/brain/reason/trip.py
pycityagent/brain/reason/user.py
pycityagent/brain/retrive/__init__.py
pycityagent/brain/retrive/social.py
pycityagent/cc/__init__.py
pycityagent/cc/cc.py
pycityagent/cc/conve.py
pycityagent/cc/idle.py
pycityagent/cc/shop.py
pycityagent/cc/trip.py
pycityagent/cc/user.py
pycityagent/hubconnector/__init__.py
pycityagent/hubconnector/hubconnector.py
pycityagent/image/__init__.py
pycityagent/image/image.py
pycityagent/st/__init__.py
pycityagent/st/st.py
pycityagent/urbanllm/__init__.py
pycityagent/urbanllm/urbanllm.py
pycityagent-1.1.11.dist-info/LICENSE
pycityagent-1.1.11.dist-info/METADATA
pycityagent-1.1.11.dist-info/WHEEL
pycityagent-1.1.11.dist-info/top_level.txt
pycityagent-1.1.11.dist-info/RECORD
