Metadata-Version: 2.1
Name: pycityagent
Version: 1.1.11
Summary: LLM-based城市模拟器agent构建库
Author-email: Yuwei Yan <pinkgranite86@gmail.com>
License: MIT License
Project-URL: Homepage, https://github.com/tsinghua-fib-lab/pycityagent
Project-URL: Repository, https://github.com/tsinghua-fib-lab/pycityagent.git
Project-URL: Issues, https://github.com/tsinghua-fib-lab/pycityagent/issues
Keywords: agent,city,LLM
Classifier: Programming Language :: Python :: 3
Classifier: Operating System :: OS Independent
Requires-Python: >=3.8
License-File: LICENSE
Requires-Dist: dashscope>=1.14.0
Requires-Dist: geojson>=3.1.0
Requires-Dist: numpy>=1.26.3
Requires-Dist: openai>=1.8.0
Requires-Dist: Pillow>=10.2.0
Requires-Dist: pycitysim>=1.12.2
Requires-Dist: citystreetview>=1.1.0
Requires-Dist: PyYAML>=6.0.1
Requires-Dist: Requests>=2.31.0
Requires-Dist: transitions>=0.9.0
